{"cameraMode":{"drawMode":0,"name":"Shaded","section":"Shading Mode"},"sceneLighting":true,"audioPlay":false,"sceneViewState":{"m_AlwaysRefresh":false,"showFog":true,"showSkybox":true,"showFlares":true,"showImageEffects":true,"showParticleSystems":true,"showVisualEffectGraphs":true,"m_FxEnabled":true},"in2DMode":false,"pivot":{"x":0.341971755027771,"y":-8.001873970031739,"z":-11.27825927734375},"rotation":{"x":-0.00942548830062151,"y":-0.959555447101593,"z":0.27988213300704958,"w":-0.03198778256773949},"size":29.6298885345459,"orthographic":false}