{"cameraMode":{"drawMode":0,"name":"Shaded","section":"Shading Mode"},"sceneLighting":false,"audioPlay":false,"sceneViewState":{"m_AlwaysRefresh":false,"showFog":true,"showSkybox":false,"showFlares":true,"showImageEffects":true,"showParticleSystems":true,"showVisualEffectGraphs":true,"m_FxEnabled":true},"in2DMode":false,"pivot":{"x":20.670000076293947,"y":1.529999852180481,"z":166.4199981689453},"rotation":{"x":0.16957512497901917,"y":-0.8297450542449951,"z":0.3942411541938782,"w":0.3578087389469147},"size":7.066768169403076,"orthographic":false}